prismacloud/api/__init__.py
prismacloud/api/pc_lib_api.py
prismacloud/api/pc_lib_utility.py
prismacloud/api/version.py
prismacloud/api/cspm/__init__.py
prismacloud/api/cspm/_endpoints.py
prismacloud/api/cspm/_extended.py
prismacloud/api/cspm/cspm.py
prismacloud/api/cwpp/__init__.py
prismacloud/api/cwpp/_audits.py
prismacloud/api/cwpp/_cloud.py
prismacloud/api/cwpp/_collections.py
prismacloud/api/cwpp/_containers.py
prismacloud/api/cwpp/_credentials.py
prismacloud/api/cwpp/_defenders.py
prismacloud/api/cwpp/_feeds.py
prismacloud/api/cwpp/_hosts.py
prismacloud/api/cwpp/_images.py
prismacloud/api/cwpp/_logs.py
prismacloud/api/cwpp/_policies.py
prismacloud/api/cwpp/_registry.py
prismacloud/api/cwpp/_scans.py
prismacloud/api/cwpp/_serverless.py
prismacloud/api/cwpp/_settings.py
prismacloud/api/cwpp/_stats.py
prismacloud/api/cwpp/_status.py
prismacloud/api/cwpp/_tags.py
prismacloud/api/cwpp/_vms.py
prismacloud/api/cwpp/cwpp.py
prismacloud/api/pccs/__init__.py
prismacloud/api/pccs/_checkov_version.py
prismacloud/api/pccs/_code_policies.py
prismacloud/api/pccs/_errors.py
prismacloud/api/pccs/_fixes.py
prismacloud/api/pccs/_packages.py
prismacloud/api/pccs/_repositories.py
prismacloud/api/pccs/_rules.py
prismacloud/api/pccs/_scans.py
prismacloud/api/pccs/_suppressions.py
prismacloud/api/pccs/pccs.py
scripts/examples/pcs_vuln_container_with_cve_2022_22965.py
tests/data.py
tests/test_cwpp_cwpp.py
tests/test_unit.py
prismacloud_api-5.3.0.dist-info/LICENSE
prismacloud_api-5.3.0.dist-info/METADATA
prismacloud_api-5.3.0.dist-info/WHEEL
prismacloud_api-5.3.0.dist-info/top_level.txt
prismacloud_api-5.3.0.dist-info/RECORD
