Metadata-Version: 2.2
Name: prismacloud-api
Version: 5.3.0
Summary: Prisma Cloud API SDK for Python
Home-page: https://github.com/PaloAltoNetworks/prismacloud-api-python
Author: Tom Kishel
Author-email: tkishel@paloaltonetworks.com
Classifier: Programming Language :: Python :: 3
Classifier: License :: OSI Approved :: MIT License
Classifier: Operating System :: OS Independent
Classifier: Topic :: Utilities
Requires-Python: >=3.6
License-File: LICENSE
Provides-Extra: test
Requires-Dist: coverage==7.6.10; extra == "test"
Requires-Dist: responses==0.25.3; extra == "test"
Dynamic: author
Dynamic: author-email
Dynamic: classifier
Dynamic: description
Dynamic: description-content-type
Dynamic: home-page
Dynamic: requires-python
Dynamic: summary
